httpstatusx/__init__.py
httpstatusx/cli.py
httpstatusx/core.py
httpstatusx/data.py
httpstatusx/exceptions.py
httpstatusx/frameworks.py
httpstatusx/fuzzy.py
httpstatusx-1.0.2.dist-info/licenses/LICENSE
httpstatusx-1.0.2.dist-info/METADATA
httpstatusx-1.0.2.dist-info/WHEEL
httpstatusx-1.0.2.dist-info/entry_points.txt
httpstatusx-1.0.2.dist-info/top_level.txt
httpstatusx-1.0.2.dist-info/RECORD
