Metadata-Version: 2.4
Name: httpstatusx
Version: 1.0.2
Summary: Semantic, bidirectional HTTP status abstraction with CLI and framework support
Author-email: Koda Adam <adam.koda2995@gmail.com>
License: MIT
Project-URL: Homepage, https://github.com/Adamkoda2306/httpstatusx
Project-URL: Repository, https://github.com/Adamkoda2306/httpstatusx
Project-URL: Issues, https://github.com/Adamkoda2306/httpstatusx/issues
Project-URL: Documentation, https://github.com/Adamkoda2306/httpstatusx/blob/main/USAGE.md
Requires-Python: >=3.10
License-File: LICENSE
Requires-Dist: colorama
Dynamic: license-file
